{"data":{"site":{"siteMetadata":{"title":"Gatsby Default Starter"}},"github":{"viewer":{"name":"Vitor Ruiz Leonel","repositories":{"nodes":[{"name":"ml-test"},{"name":"chico"},{"name":"vanilla-carousel"},{"name":"PureJSCarousel"},{"name":"Altran"},{"name":"react-simples"},{"name":"react-tutorial"},{"name":"javascript30"},{"name":"easynvest-test"},{"name":"mollynho_bot"},{"name":"mollynho_bot"},{"name":"curso-react-redux"},{"name":"exercicios_webpack"},{"name":"exercicios_react"},{"name":"todo-app"},{"name":"enzyme"},{"name":"NuMarket"},{"name":"react-app-root"},{"name":"oab-na-medida"},{"name":"grupozap-code-challenge"},{"name":"ze-delivery-code-challenge"},{"name":"shell-node"},{"name":"c4-api-banner"},{"name":"bot-hera"},{"name":"vrleonel.github.io"},{"name":"gatsby-site"},{"name":"woliveiras.github.io"},{"name":"gatsby-github"},{"name":"proftatianalopes"},{"name":"jogo-da-velha"}]}}}}}